<?xml version="1.0" standalone="yes"?>
<dsCourses xmlns="http://tempuri.org/dsCourses.xsd">
  <tblCourses>
    <ID>1</ID>
    <courseName>CIS355A</courseName>
    <courseLanguage>Java</courseLanguage>
    <courseDate>2018-09-01T00:00:00-05:00</courseDate>
    <userID>1</userID>
  </tblCourses>
  <tblCourses>
    <ID>3</ID>
    <courseName>WEB250</courseName>
    <courseLanguage>HTML</courseLanguage>
    <courseDate>2018-09-12T00:00:00-05:00</courseDate>
    <userID>1</userID>
  </tblCourses>
</dsCourses>